mySA/array_with_mem/pe.v
module pe #(
  parameter integer DATA_WIDTH = 10
) (
    input clk,
    input compute,
    input  logic unsigned [DATA_WIDTH-1:0] A,
    input  logic unsigned [DATA_WIDTH-1:0] B,
    output logic unsigned [DATA_WIDTH-1:0]   X,
    input init
);
    reg [(2*DATA_WIDTH)+1:0] state;

    always @ (posedge clk) 
        if (init)
            state <= 0;
        else
        if (compute)
            // temp = A * B;
            state <= (A*B);

    assign X = state[DATA_WIDTH-1:0];

endmodule

mySA/array_with_mem/pe_array.v

module ram(
    input clk,
    input we,
    input  logic unsigned [DATA_WIDTH-1:0] din,
    input  logic unsigned [ADDR_WIDTH-1:0] addr,
    output logic unsigned [DATA_WIDTH-1:0] dout
);
    parameter integer DATA_WIDTH = 10;
    parameter integer ADDR_WIDTH = 4;

    logic unsigned [DATA_WIDTH-1:0] mem [(2**ADDR_WIDTH)-1:0];

    always_ff @(posedge clk) begin
        if (we) begin
            mem[addr] <= din;
        end
        dout <= mem[addr];
    end

endmodule

module array #(
    parameter integer NUM_PES = 4,
    parameter integer DATA_WIDTH = 10,
    parameter integer ADDR_WIDTH = 4
)(
    input  logic clk,
    input  logic compute,
    input  logic init,

    // RAM A: one DATA_WIDTH word per address, feeds the first PE
    input  logic we_a,
    input  logic unsigned [ADDR_WIDTH-1:0] addr_a,
    input  logic unsigned [DATA_WIDTH-1:0] din_a,

    // RAM B: one word per address holding the B value of every PE
    // (PE i uses bits [i*DATA_WIDTH +: DATA_WIDTH])
    input  logic we_b,
    input  logic unsigned [ADDR_WIDTH-1:0] addr_b,
    input  logic unsigned [NUM_PES*DATA_WIDTH-1:0] din_b,

    output logic unsigned [DATA_WIDTH-1:0] array_output
);

    logic unsigned [DATA_WIDTH-1:0] pe_outputs [NUM_PES-1:0];

    logic unsigned [DATA_WIDTH-1:0]         input_a;
    logic unsigned [NUM_PES*DATA_WIDTH-1:0] ram_b_dout;
    logic unsigned [DATA_WIDTH-1:0]         input_b [NUM_PES-1:0];

    ram #(
        .DATA_WIDTH(DATA_WIDTH),
        .ADDR_WIDTH(ADDR_WIDTH)
    ) ram_a (
        .clk  (clk),
        .we   (we_a),
        .din  (din_a),
        .addr (addr_a),
        .dout (input_a)
    );

    ram #(
        .DATA_WIDTH(NUM_PES*DATA_WIDTH),
        .ADDR_WIDTH(ADDR_WIDTH)
    ) ram_b (
        .clk  (clk),
        .we   (we_b),
        .din  (din_b),
        .addr (addr_b),
        .dout (ram_b_dout)
    );

    genvar i;

    generate
        for (i = 0; i < NUM_PES; i++) begin : gen_unpack_b
            assign input_b[i] = ram_b_dout[i*DATA_WIDTH +: DATA_WIDTH];
        end
    endgenerate

    generate
        for (i = 0; i < NUM_PES; i++) begin : gen_pes

            if (i == 0) begin : first_pe

                pe #(
                    .DATA_WIDTH(DATA_WIDTH)
                ) pe_inst (
                    .clk     (clk),
                    .compute (compute),
                    .init    (init),
                    .A       (input_a),
                    .B       (input_b[i]),
                    .X       (pe_outputs[i])
                );

            end
            else begin : other_pes

                pe #(
                    .DATA_WIDTH(DATA_WIDTH)
                ) pe_inst (
                    .clk     (clk),
                    .compute (compute),
                    .init    (init),
                    .A       (pe_outputs[i-1]),
                    .B       (input_b[i]),
                    .X       (pe_outputs[i])
                );

            end
        end
    endgenerate

    assign array_output = pe_outputs[NUM_PES-1];

endmodule

mySA/array_with_mem/dump.vcd
$version Generated by VerilatedVcd $end
$timescale 1ps $end
 $scope module  $end
  $var wire 1 # clk $end
  $var wire 1 $ compute $end
  $var wire 1 % init $end
  $var wire 1 & we_a $end
  $var wire 4 ' addr_a [3:0] $end
  $var wire 10 ( din_a [9:0] $end
  $var wire 1 ) we_b $end
  $var wire 4 * addr_b [3:0] $end
  $var wire 40 + din_b [39:0] $end
  $var wire 10 - array_output [9:0] $end
  $scope module array $end
   $var wire 32 >! NUM_PES [31:0] $end
   $var wire 32 ?! DATA_WIDTH [31:0] $end
   $var wire 32 >! ADDR_WIDTH [31:0] $end
   $var wire 1 . clk $end
   $var wire 1 / compute $end
   $var wire 1 0 init $end
   $var wire 1 1 we_a $end
   $var wire 4 2 addr_a [3:0] $end
   $var wire 10 3 din_a [9:0] $end
   $var wire 1 4 we_b $end
   $var wire 4 5 addr_b [3:0] $end
   $var wire 40 6 din_b [39:0] $end
   $var wire 10 8 array_output [9:0] $end
   $var wire 10 9 pe_outputs[0] [9:0] $end
   $var wire 10 : pe_outputs[1] [9:0] $end
   $var wire 10 ; pe_outputs[2] [9:0] $end
   $var wire 10 < pe_outputs[3] [9:0] $end
   $var wire 10 = input_a [9:0] $end
   $var wire 40 > ram_b_dout [39:0] $end
   $var wire 10 @ input_b[0] [9:0] $end
   $var wire 10 A input_b[1] [9:0] $end
   $var wire 10 B input_b[2] [9:0] $end
   $var wire 10 C input_b[3] [9:0] $end
   $scope module gen_pes[0] $end
    $scope module first_pe $end
     $scope module pe_inst $end
      $var wire 32 ?! DATA_WIDTH [31:0] $end
      $var wire 1 D clk $end
      $var wire 1 E compute $end
      $var wire 10 F A [9:0] $end
      $var wire 10 G B [9:0] $end
      $var wire 10 H X [9:0] $end
      $var wire 1 I init $end
      $var wire 22 J state [21:0] $end
     $upscope $end
    $upscope $end
   $upscope $end
   $scope module gen_pes[1] $end
    $scope module other_pes $end
     $scope module pe_inst $end
      $var wire 32 ?! DATA_WIDTH [31:0] $end
      $var wire 1 K clk $end
      $var wire 1 L compute $end
      $var wire 10 M A [9:0] $end
      $var wire 10 N B [9:0] $end
      $var wire 10 O X [9:0] $end
      $var wire 1 P init $end
      $var wire 22 Q state [21:0] $end
     $upscope $end
    $upscope $end
   $upscope $end
   $scope module gen_pes[2] $end
    $scope module other_pes $end
     $scope module pe_inst $end
      $var wire 32 ?! DATA_WIDTH [31:0] $end
      $var wire 1 R clk $end
      $var wire 1 S compute $end
      $var wire 10 T A [9:0] $end
      $var wire 10 U B [9:0] $end
      $var wire 10 V X [9:0] $end
      $var wire 1 W init $end
      $var wire 22 X state [21:0] $end
     $upscope $end
    $upscope $end
   $upscope $end
   $scope module gen_pes[3] $end
    $scope module other_pes $end
     $scope module pe_inst $end
      $var wire 32 ?! DATA_WIDTH [31:0] $end
      $var wire 1 Y clk $end
      $var wire 1 Z compute $end
      $var wire 10 [ A [9:0] $end
      $var wire 10 \ B [9:0] $end
      $var wire 10 ] X [9:0] $end
      $var wire 1 ^ init $end
      $var wire 22 _ state [21:0] $end
     $upscope $end
    $upscope $end
   $upscope $end
   $scope module ram_a $end
    $var wire 1 ` clk $end
    $var wire 1 a we $end
    $var wire 10 b din [9:0] $end
    $var wire 4 c addr [3:0] $end
    $var wire 10 d dout [9:0] $end
    $var wire 32 ?! DATA_WIDTH [31:0] $end
    $var wire 32 >! ADDR_WIDTH [31:0] $end
    $var wire 10 e mem[0] [9:0] $end
    $var wire 10 f mem[1] [9:0] $end
    $var wire 10 g mem[2] [9:0] $end
    $var wire 10 h mem[3] [9:0] $end
    $var wire 10 i mem[4] [9:0] $end
    $var wire 10 j mem[5] [9:0] $end
    $var wire 10 k mem[6] [9:0] $end
    $var wire 10 l mem[7] [9:0] $end
    $var wire 10 m mem[8] [9:0] $end
    $var wire 10 n mem[9] [9:0] $end
    $var wire 10 o mem[10] [9:0] $end
    $var wire 10 p mem[11] [9:0] $end
    $var wire 10 q mem[12] [9:0] $end
    $var wire 10 r mem[13] [9:0] $end
    $var wire 10 s mem[14] [9:0] $end
    $var wire 10 t mem[15] [9:0] $end
   $upscope $end
   $scope module ram_b $end
    $var wire 1 u clk $end
    $var wire 1 v we $end
    $var wire 40 w din [39:0] $end
    $var wire 4 y addr [3:0] $end
    $var wire 40 z dout [39:0] $end
    $var wire 32 @! DATA_WIDTH [31:0] $end
    $var wire 32 >! ADDR_WIDTH [31:0] $end
    $var wire 40 | mem[0] [39:0] $end
    $var wire 40 ~ mem[1] [39:0] $end
    $var wire 40 "! mem[2] [39:0] $end
    $var wire 40 $! mem[3] [39:0] $end
    $var wire 40 &! mem[4] [39:0] $end
    $var wire 40 (! mem[5] [39:0] $end
    $var wire 40 *! mem[6] [39:0] $end
    $var wire 40 ,! mem[7] [39:0] $end
    $var wire 40 .! mem[8] [39:0] $end
    $var wire 40 0! mem[9] [39:0] $end
    $var wire 40 2! mem[10] [39:0] $end
    $var wire 40 4! mem[11] [39:0] $end
    $var wire 40 6! mem[12] [39:0] $end
    $var wire 40 8! mem[13] [39:0] $end
    $var wire 40 :! mem[14] [39:0] $end
    $var wire 40 <! mem[15] [39:0] $end
   $upscope $end
  $upscope $end
 $upscope $end
$enddefinitions $end


#0
0#
0$
0%
1&
b0000 '
b0000000001 (
1)
b0000 *
b0000000100000000001100000000100000000001 +
b0000000000 -
0.
0/
00
11
b0000 2
b0000000001 3
14
b0000 5
b0000000100000000001100000000100000000001 6
b0000000000 8
b0000000000 9
b0000000000 :
b0000000000 ;
b0000000000 <
b0000000000 =
b0000000000000000000000000000000000000000 >
b0000000000 @
b0000000000 A
b0000000000 B
b0000000000 C
0D
0E
b0000000000 F
b0000000000 G
b0000000000 H
0I
b0000000000000000000000 J
0K
0L
b0000000000 M
b0000000000 N
b0000000000 O
0P
b0000000000000000000000 Q
0R
0S
b0000000000 T
b0000000000 U
b0000000000 V
0W
b0000000000000000000000 X
0Y
0Z
b0000000000 [
b0000000000 \
b0000000000 ]
0^
b0000000000000000000000 _
0`
1a
b0000000001 b
b0000 c
b0000000000 d
b0000000000 e
b0000000000 f
b0000000000 g
b0000000000 h
b0000000000 i
b0000000000 j
b0000000000 k
b0000000000 l
b0000000000 m
b0000000000 n
b0000000000 o
b0000000000 p
b0000000000 q
b0000000000 r
b0000000000 s
b0000000000 t
0u
1v
b0000000100000000001100000000100000000001 w
b0000 y
b0000000000000000000000000000000000000000 z
b0000000000000000000000000000000000000000 |
b0000000000000000000000000000000000000000 ~
b0000000000000000000000000000000000000000 "!
b0000000000000000000000000000000000000000 $!
b0000000000000000000000000000000000000000 &!
b0000000000000000000000000000000000000000 (!
b0000000000000000000000000000000000000000 *!
b0000000000000000000000000000000000000000 ,!
b0000000000000000000000000000000000000000 .!
b0000000000000000000000000000000000000000 0!
b0000000000000000000000000000000000000000 2!
b0000000000000000000000000000000000000000 4!
b0000000000000000000000000000000000000000 6!
b0000000000000000000000000000000000000000 8!
b0000000000000000000000000000000000000000 :!
b0000000000000000000000000000000000000000 <!
b00000000000000000000000000000100 >!
b00000000000000000000000000001010 ?!
b00000000000000000000000000101000 @!
#1000
1#
1.
1D
1K
1R
1Y
1`
b0000000001 e
1u
b0000000100000000001100000000100000000001 |
#2000
0#
0&
0)
0.
01
04
0D
0K
0R
0Y
0`
0a
0u
0v
#3000
1#
1.
b0000000001 =
b0000000100000000001100000000100000000001 >
b0000000001 @
b0000000010 A
b0000000011 B
b0000000100 C
1D
b0000000001 F
b0000000001 G
1K
b0000000010 N
1R
b0000000011 U
1Y
b0000000100 \
1`
b0000000001 d
1u
b0000000100000000001100000000100000000001 z
#4000
0#
1%
0.
10
0D
1I
0K
1P
0R
1W
0Y
1^
0`
0u
#5000
1#
0%
1.
00
1D
0I
1K
0P
1R
0W
1Y
0^
1`
1u
#6000
0#
1$
0.
1/
0D
1E
0K
1L
0R
1S
0Y
1Z
0`
0u
#7000
1#
1.
b0000000001 9
1D
b0000000001 H
b0000000000000000000001 J
1K
b0000000001 M
1R
1Y
1`
1u
#8000
0#
0.
0D
0K
0R
0Y
0`
0u
#9000
1#
1.
b0000000010 :
1D
1K
b0000000010 O
b0000000000000000000010 Q
1R
b0000000010 T
1Y
1`
1u
#10000
0#
0.
0D
0K
0R
0Y
0`
0u
#11000
1#
1.
b0000000110 ;
1D
1K
1R
b0000000110 V
b0000000000000000000110 X
1Y
b0000000110 [
1`
1u
#12000
0#
0.
0D
0K
0R
0Y
0`
0u
#13000
1#
b0000011000 -
1.
b0000011000 8
b0000011000 <
1D
1K
1R
1Y
b0000011000 ]
b0000000000000000011000 _
1`
1u
#14000
0#
0.
0D
0K
0R
0Y
0`
0u
#15000
1#
1.
1D
1K
1R
1Y
1`
1u
#16000
0#
1%
0.
10
0D
1I
0K
1P
0R
1W
0Y
1^
0`
0u
#17000
1#
0%
1.
00
1D
0I
1K
0P
1R
0W
1Y
0^
1`
1u
#18000
0#
0.
0D
0K
0R
0Y
0`
0u
#19000
1#
1.
1D
1K
1R
1Y
1`
1u
#20000
0#
0.
0D
0K
0R
0Y
0`
0u
#21000
1#
1.
1D
1K
1R
1Y
1`
1u
#22000
0#
0.
0D
0K
0R
0Y
0`
0u
#23000
1#
1.
1D
1K
1R
1Y
1`
1u
#24000
0#
0.
0D
0K
0R
0Y
0`
0u
#25000
1#
1.
1D
1K
1R
1Y
1`
1u
#26000
0#
0.
0D
0K
0R
0Y
0`
0u
#27000
1#
1.
1D
1K
1R
1Y
1`
1u
#28000
0#
1%
0.
10
0D
1I
0K
1P
0R
1W
0Y
1^
0`
0u
#29000
1#
0%
1.
00
1D
0I
1K
0P
1R
0W
1Y
0^
1`
1u
#30000
0#
0.
0D
0K
0R
0Y
0`
0u
#31000
1#
1.
1D
1K
1R
1Y
1`
1u
#32000
0#
0.
0D
0K
0R
0Y
0`
0u
#33000
1#
1.
1D
1K
1R
1Y
1`
1u
#34000
0#
0.
0D
0K
0R
0Y
0`
0u
#35000
1#
1.
1D
1K
1R
1Y
1`
1u
#36000
0#
0.
0D
0K
0R
0Y
0`
0u
#37000
1#
1.
1D
1K
1R
1Y
1`
1u
#38000
0#
0.
0D
0K
0R
0Y
0`
0u
#39000
1#
1.
1D
1K
1R
1Y
1`
1u
#40000
0#
1%
0.
10
0D
1I
0K
1P
0R
1W
0Y
1^
0`
0u
#41000
1#
0%
1.
00
1D
0I
1K
0P
1R
0W
1Y
0^
1`
1u
#42000
0#
0.
0D
0K
0R
0Y
0`
0u
#43000
1#
1.
1D
1K
1R
1Y
1`
1u
#44000
0#
0.
0D
0K
0R
0Y
0`
0u
#45000
1#
1.
1D
1K
1R
1Y
1`
1u
#46000
0#
0.
0D
0K
0R
0Y
0`
0u
#47000
1#
1.
1D
1K
1R
1Y
1`
1u
#48000
0#
0.
0D
0K
0R
0Y
0`
0u
#49000
1#
1.
1D
1K
1R
1Y
1`
1u
#50000
0#
0.
0D
0K
0R
0Y
0`
0u
#51000
1#
1.
1D
1K
1R
1Y
1`
1u
#52000
0#
1%
0.
10
0D
1I
0K
1P
0R
1W
0Y
1^
0`
0u
#53000
1#
0%
1.
00
1D
0I
1K
0P
1R
0W
1Y
0^
1`
1u
#54000
0#
0.
0D
0K
0R
0Y
0`
0u
#55000
1#
1.
1D
1K
1R
1Y
1`
1u
#56000
0#
0.
0D
0K
0R
0Y
0`
0u
#57000
1#
1.
1D
1K
1R
1Y
1`
1u
#58000
0#
0.
0D
0K
0R
0Y
0`
0u
#59000
1#
1.
1D
1K
1R
1Y
1`
1u
#60000
0#
0.
0D
0K
0R
0Y
0`
0u
#61000
1#
1.
1D
1K
1R
1Y
1`
1u
#62000
0#
0.
0D
0K
0R
0Y
0`
0u
#63000
1#
1.
1D
1K
1R
1Y
1`
1u
#64000
0#
1%
0.
10
0D
1I
0K
1P
0R
1W
0Y
1^
0`
0u
#65000
1#
0%
1.
00
1D
0I
1K
0P
1R
0W
1Y
0^
1`
1u
#66000
0#
0.
0D
0K
0R
0Y
0`
0u
#67000
1#
1.
1D
1K
1R
1Y
1`
1u
#68000
0#
0.
0D
0K
0R
0Y
0`
0u
#69000
1#
1.
1D
1K
1R
1Y
1`
1u
#70000
0#
0.
0D
0K
0R
0Y
0`
0u
#71000
1#
1.
1D
1K
1R
1Y
1`
1u
#72000
0#
0.
0D
0K
0R
0Y
0`
0u
#73000
1#
1.
1D
1K
1R
1Y
1`
1u
#74000
0#
0.
0D
0K
0R
0Y
0`
0u
#75000
1#
1.
1D
1K
1R
1Y
1`
1u
#76000
0#
1%
0.
10
0D
1I
0K
1P
0R
1W
0Y
1^
0`
0u
#77000
1#
0%
1.
00
1D
0I
1K
0P
1R
0W
1Y
0^
1`
1u
#78000
0#
0.
0D
0K
0R
0Y
0`
0u
#79000
1#
1.
1D
1K
1R
1Y
1`
1u
#80000
0#
0.
0D
0K
0R
0Y
0`
0u
#81000
1#
1.
1D
1K
1R
1Y
1`
1u
#82000
0#
0.
0D
0K
0R
0Y
0`
0u
#83000
1#
1.
1D
1K
1R
1Y
1`
1u
#84000
0#
0.
0D
0K
0R
0Y
0`
0u
#85000
1#
1.
1D
1K
1R
1Y
1`
1u
#86000
0#
0.
0D
0K
0R
0Y
0`
0u
#87000
1#
1.
1D
1K
1R
1Y
1`
1u
#88000
0#
1%
0.
10
0D
1I
0K
1P
0R
1W
0Y
1^
0`
0u
#89000
1#
0%
1.
00
1D
0I
1K
0P
1R
0W
1Y
0^
1`
1u
#90000
0#
0.
0D
0K
0R
0Y
0`
0u
#91000
1#
1.
1D
1K
1R
1Y
1`
1u
#92000
0#
0.
0D
0K
0R
0Y
0`
0u
#93000
1#
1.
1D
1K
1R
1Y
1`
1u
#94000
0#
0.
0D
0K
0R
0Y
0`
0u
#95000
1#
1.
1D
1K
1R
1Y
1`
1u
#96000
0#
0.
0D
0K
0R
0Y
0`
0u
#97000
1#
1.
1D
1K
1R
1Y
1`
1u
#98000
0#
0.
0D
0K
0R
0Y
0`
0u
#99000
1#
1.
1D
1K
1R
1Y
1`
1u
#100000
0#
1%
0.
10
0D
1I
0K
1P
0R
1W
0Y
1^
0`
0u
#101000
1#
0%
1.
00
1D
0I
1K
0P
1R
0W
1Y
0^
1`
1u
#102000
0#
0.
0D
0K
0R
0Y
0`
0u
#103000
1#
1.
1D
1K
1R
1Y
1`
1u
#104000
0#
0.
0D
0K
0R
0Y
0`
0u
#105000
1#
1.
1D
1K
1R
1Y
1`
1u
#106000
0#
0.
0D
0K
0R
0Y
0`
0u
#107000
1#
1.
1D
1K
1R
1Y
1`
1u
#108000
0#
0.
0D
0K
0R
0Y
0`
0u
#109000
1#
1.
1D
1K
1R
1Y
1`
1u
#110000
0#
0.
0D
0K
0R
0Y
0`
0u
#111000
1#
1.
1D
1K
1R
1Y
1`
1u
#112000
0#
1%
0.
10
0D
1I
0K
1P
0R
1W
0Y
1^
0`
0u
#113000
1#
0%
1.
00
1D
0I
1K
0P
1R
0W
1Y
0^
1`
1u
