mySA/array_with_mem/pe.v
module pe #(
  parameter integer DATA_WIDTH = 10
) (
    input clk,
    input compute,
    input  logic unsigned [DATA_WIDTH-1:0] A,
    input  logic unsigned [DATA_WIDTH-1:0] B,
    output logic unsigned [DATA_WIDTH-1:0]   X,
    input init
);
    reg [(2*DATA_WIDTH)+1:0] state;

    always @ (posedge clk) 
        if (init)
            state <= 0;
        else
        if (compute)
            // temp = A * B;
            state <= (A*B);

    assign X = state[DATA_WIDTH-1:0];

endmodule

mySA/PE/pe_array.v
module array #(
    parameter integer NUM_PES = 4,
    parameter integer DATA_WIDTH = 10
)(
    input  logic clk,
    input  logic compute,
    input  logic init,

    input  logic unsigned [DATA_WIDTH-1:0] input_a,
    input  logic unsigned [DATA_WIDTH-1:0] input_b [NUM_PES-1:0],

    output logic unsigned [DATA_WIDTH-1:0] array_output
);

    logic unsigned [DATA_WIDTH-1:0] pe_outputs [NUM_PES-1:0];

    genvar i;

    generate
        for (i = 0; i < NUM_PES; i++) begin : gen_pes

            if (i == 0) begin : first_pe

                pe #(
                    .DATA_WIDTH(DATA_WIDTH)
                ) pe_inst (
                    .clk     (clk),
                    .compute (compute),
                    .init    (init),
                    .A       (input_a),
                    .B       (input_b[i]),
                    .X       (pe_outputs[i])
                );

            end
            else begin : other_pes

                pe #(
                    .DATA_WIDTH(DATA_WIDTH)
                ) pe_inst (
                    .clk     (clk),
                    .compute (compute),
                    .init    (init),
                    .A       (pe_outputs[i-1]),
                    .B       (input_b[i]),
                    .X       (pe_outputs[i])
                );

            end
        end
    endgenerate

    assign array_output = pe_outputs[NUM_PES-1];

endmodule

mySA/PE/dump.vcd
$version Generated by VerilatedVcd $end
$timescale 1ps $end
 $scope module  $end
  $var wire 1 # clk $end
  $var wire 1 $ compute $end
  $var wire 1 % init $end
  $var wire 10 & input_a [9:0] $end
  $var wire 10 ' input_b[0] [9:0] $end
  $var wire 10 ( input_b[1] [9:0] $end
  $var wire 10 ) input_b[2] [9:0] $end
  $var wire 10 * input_b[3] [9:0] $end
  $var wire 10 + array_output [9:0] $end
  $scope module array $end
   $var wire 32 U NUM_PES [31:0] $end
   $var wire 32 V DATA_WIDTH [31:0] $end
   $var wire 1 , clk $end
   $var wire 1 - compute $end
   $var wire 1 . init $end
   $var wire 10 / input_a [9:0] $end
   $var wire 10 0 input_b[0] [9:0] $end
   $var wire 10 1 input_b[1] [9:0] $end
   $var wire 10 2 input_b[2] [9:0] $end
   $var wire 10 3 input_b[3] [9:0] $end
   $var wire 10 4 array_output [9:0] $end
   $var wire 10 5 pe_outputs[0] [9:0] $end
   $var wire 10 6 pe_outputs[1] [9:0] $end
   $var wire 10 7 pe_outputs[2] [9:0] $end
   $var wire 10 8 pe_outputs[3] [9:0] $end
   $scope module gen_pes[0] $end
    $scope module first_pe $end
     $scope module pe_inst $end
      $var wire 32 V DATA_WIDTH [31:0] $end
      $var wire 1 9 clk $end
      $var wire 1 : compute $end
      $var wire 10 ; A [9:0] $end
      $var wire 10 < B [9:0] $end
      $var wire 10 = X [9:0] $end
      $var wire 1 > init $end
      $var wire 22 ? state [21:0] $end
     $upscope $end
    $upscope $end
   $upscope $end
   $scope module gen_pes[1] $end
    $scope module other_pes $end
     $scope module pe_inst $end
      $var wire 32 V DATA_WIDTH [31:0] $end
      $var wire 1 @ clk $end
      $var wire 1 A compute $end
      $var wire 10 B A [9:0] $end
      $var wire 10 C B [9:0] $end
      $var wire 10 D X [9:0] $end
      $var wire 1 E init $end
      $var wire 22 F state [21:0] $end
     $upscope $end
    $upscope $end
   $upscope $end
   $scope module gen_pes[2] $end
    $scope module other_pes $end
     $scope module pe_inst $end
      $var wire 32 V DATA_WIDTH [31:0] $end
      $var wire 1 G clk $end
      $var wire 1 H compute $end
      $var wire 10 I A [9:0] $end
      $var wire 10 J B [9:0] $end
      $var wire 10 K X [9:0] $end
      $var wire 1 L init $end
      $var wire 22 M state [21:0] $end
     $upscope $end
    $upscope $end
   $upscope $end
   $scope module gen_pes[3] $end
    $scope module other_pes $end
     $scope module pe_inst $end
      $var wire 32 V DATA_WIDTH [31:0] $end
      $var wire 1 N clk $end
      $var wire 1 O compute $end
      $var wire 10 P A [9:0] $end
      $var wire 10 Q B [9:0] $end
      $var wire 10 R X [9:0] $end
      $var wire 1 S init $end
      $var wire 22 T state [21:0] $end
     $upscope $end
    $upscope $end
   $upscope $end
  $upscope $end
 $upscope $end
$enddefinitions $end


#0
0#
0$
0%
b0000000001 &
b0000000001 '
b0000000010 (
b0000000011 )
b0000000100 *
b0000000000 +
0,
0-
0.
b0000000001 /
b0000000001 0
b0000000010 1
b0000000011 2
b0000000100 3
b0000000000 4
b0000000000 5
b0000000000 6
b0000000000 7
b0000000000 8
09
0:
b0000000001 ;
b0000000001 <
b0000000000 =
0>
b0000000000000000000000 ?
0@
0A
b0000000000 B
b0000000010 C
b0000000000 D
0E
b0000000000000000000000 F
0G
0H
b0000000000 I
b0000000011 J
b0000000000 K
0L
b0000000000000000000000 M
0N
0O
b0000000000 P
b0000000100 Q
b0000000000 R
0S
b0000000000000000000000 T
b00000000000000000000000000000100 U
b00000000000000000000000000001010 V
#1000
1#
1,
19
1@
1G
1N
#2000
0#
1%
0,
1.
09
1>
0@
1E
0G
1L
0N
1S
#3000
1#
0%
1,
0.
19
0>
1@
0E
1G
0L
1N
0S
#4000
0#
1$
0,
1-
09
1:
0@
1A
0G
1H
0N
1O
#5000
1#
1,
b0000000001 5
19
b0000000001 =
b0000000000000000000001 ?
1@
b0000000001 B
1G
1N
#6000
0#
0,
09
0@
0G
0N
#7000
1#
1,
b0000000010 6
19
1@
b0000000010 D
b0000000000000000000010 F
1G
b0000000010 I
1N
#8000
0#
0,
09
0@
0G
0N
#9000
1#
1,
b0000000110 7
19
1@
1G
b0000000110 K
b0000000000000000000110 M
1N
b0000000110 P
#10000
0#
0,
09
0@
0G
0N
#11000
1#
b0000011000 +
1,
b0000011000 4
b0000011000 8
19
1@
1G
1N
b0000011000 R
b0000000000000000011000 T
#12000
0#
1%
0,
1.
09
1>
0@
1E
0G
1L
0N
1S
#13000
1#
0%
1,
0.
19
0>
1@
0E
1G
0L
1N
0S
#14000
0#
0,
09
0@
0G
0N
#15000
1#
1,
19
1@
1G
1N
#16000
0#
0,
09
0@
0G
0N
#17000
1#
1,
19
1@
1G
1N
#18000
0#
0,
09
0@
0G
0N
#19000
1#
1,
19
1@
1G
1N
#20000
0#
0,
09
0@
0G
0N
#21000
1#
1,
19
1@
1G
1N
#22000
0#
1%
0,
1.
09
1>
0@
1E
0G
1L
0N
1S
#23000
1#
0%
1,
0.
19
0>
1@
0E
1G
0L
1N
0S
#24000
0#
0,
09
0@
0G
0N
#25000
1#
1,
19
1@
1G
1N
#26000
0#
0,
09
0@
0G
0N
#27000
1#
1,
19
1@
1G
1N
#28000
0#
0,
09
0@
0G
0N
#29000
1#
1,
19
1@
1G
1N
#30000
0#
0,
09
0@
0G
0N
#31000
1#
1,
19
1@
1G
1N
#32000
0#
1%
0,
1.
09
1>
0@
1E
0G
1L
0N
1S
#33000
1#
0%
1,
0.
19
0>
1@
0E
1G
0L
1N
0S
#34000
0#
0,
09
0@
0G
0N
#35000
1#
1,
19
1@
1G
1N
#36000
0#
0,
09
0@
0G
0N
#37000
1#
1,
19
1@
1G
1N
#38000
0#
0,
09
0@
0G
0N
#39000
1#
1,
19
1@
1G
1N
#40000
0#
0,
09
0@
0G
0N
#41000
1#
1,
19
1@
1G
1N
#42000
0#
1%
0,
1.
09
1>
0@
1E
0G
1L
0N
1S
#43000
1#
0%
1,
0.
19
0>
1@
0E
1G
0L
1N
0S
#44000
0#
0,
09
0@
0G
0N
#45000
1#
1,
19
1@
1G
1N
#46000
0#
0,
09
0@
0G
0N
#47000
1#
1,
19
1@
1G
1N
#48000
0#
0,
09
0@
0G
0N
#49000
1#
1,
19
1@
1G
1N
#50000
0#
0,
09
0@
0G
0N
#51000
1#
1,
19
1@
1G
1N
#52000
0#
1%
0,
1.
09
1>
0@
1E
0G
1L
0N
1S
#53000
1#
0%
1,
0.
19
0>
1@
0E
1G
0L
1N
0S
#54000
0#
0,
09
0@
0G
0N
#55000
1#
1,
19
1@
1G
1N
#56000
0#
0,
09
0@
0G
0N
#57000
1#
1,
19
1@
1G
1N
#58000
0#
0,
09
0@
0G
0N
#59000
1#
1,
19
1@
1G
1N
#60000
0#
0,
09
0@
0G
0N
#61000
1#
1,
19
1@
1G
1N
#62000
0#
1%
0,
1.
09
1>
0@
1E
0G
1L
0N
1S
#63000
1#
0%
1,
0.
19
0>
1@
0E
1G
0L
1N
0S
#64000
0#
0,
09
0@
0G
0N
#65000
1#
1,
19
1@
1G
1N
#66000
0#
0,
09
0@
0G
0N
#67000
1#
1,
19
1@
1G
1N
#68000
0#
0,
09
0@
0G
0N
#69000
1#
1,
19
1@
1G
1N
#70000
0#
0,
09
0@
0G
0N
#71000
1#
1,
19
1@
1G
1N
#72000
0#
1%
0,
1.
09
1>
0@
1E
0G
1L
0N
1S
#73000
1#
0%
1,
0.
19
0>
1@
0E
1G
0L
1N
0S
#74000
0#
0,
09
0@
0G
0N
#75000
1#
1,
19
1@
1G
1N
#76000
0#
0,
09
0@
0G
0N
#77000
1#
1,
19
1@
1G
1N
#78000
0#
0,
09
0@
0G
0N
#79000
1#
1,
19
1@
1G
1N
#80000
0#
0,
09
0@
0G
0N
#81000
1#
1,
19
1@
1G
1N
#82000
0#
1%
0,
1.
09
1>
0@
1E
0G
1L
0N
1S
#83000
1#
0%
1,
0.
19
0>
1@
0E
1G
0L
1N
0S
#84000
0#
0,
09
0@
0G
0N
#85000
1#
1,
19
1@
1G
1N
#86000
0#
0,
09
0@
0G
0N
#87000
1#
1,
19
1@
1G
1N
#88000
0#
0,
09
0@
0G
0N
#89000
1#
1,
19
1@
1G
1N
#90000
0#
0,
09
0@
0G
0N
#91000
1#
1,
19
1@
1G
1N
#92000
0#
1%
0,
1.
09
1>
0@
1E
0G
1L
0N
1S
#93000
1#
0%
1,
0.
19
0>
1@
0E
1G
0L
1N
0S
