mySA/PE/pe.v
module pe #(
  parameter integer DATA_WIDTH = 10
) (
    input clk,
    input compute,
    input  logic unsigned [DATA_WIDTH-1:0] A,
    input  logic unsigned [DATA_WIDTH-1:0] B,
    input  logic unsigned [DATA_WIDTH-1:0] C,
    output logic unsigned [(2*DATA_WIDTH)+1:0]   X
);
    reg [(2*DATA_WIDTH)+1:0] state;

    always @ (posedge clk) 
        if (compute)
            // temp = A * B;
            state <= (A * B) + ((2*DATA_WIDTH)+1)'(C);

    assign X = state;

endmodule

mySA/PE/dump.vcd
$version Generated by VerilatedVcd $end
$timescale 1ps $end
 $scope module  $end
  $var wire 1 # clk $end
  $var wire 1 $ compute $end
  $var wire 10 % A [9:0] $end
  $var wire 10 & B [9:0] $end
  $var wire 10 ' C [9:0] $end
  $var wire 22 ( X [21:0] $end
  $scope module pe $end
   $var wire 32 0 DATA_WIDTH [31:0] $end
   $var wire 1 ) clk $end
   $var wire 1 * compute $end
   $var wire 10 + A [9:0] $end
   $var wire 10 , B [9:0] $end
   $var wire 10 - C [9:0] $end
   $var wire 22 . X [21:0] $end
   $var wire 22 / state [21:0] $end
  $upscope $end
 $upscope $end
$enddefinitions $end


#0
0#
0$
b1111111111 %
b1111111111 &
b0000000000 '
b0000000000000000000000 (
0)
0*
b1111111111 +
b1111111111 ,
b0000000000 -
b0000000000000000000000 .
b0000000000000000000000 /
b00000000000000000000000000001010 0
#1000
1#
1)
#2000
0#
0)
#3000
1#
1)
#4000
0#
0)
#5000
1#
1)
#6000
0#
0)
#7000
1#
1)
#8000
0#
0)
#9000
1#
1)
#10000
0#
0)
#11000
1#
1)
#12000
0#
0)
#13000
1#
1)
#14000
0#
0)
#15000
1#
1)
#16000
0#
0)
#17000
1#
1)
#18000
0#
0)
#19000
1#
1)
#20000
0#
1$
0)
1*
#21000
1#
b0011111111100000000001 (
1)
b0011111111100000000001 .
b0011111111100000000001 /
#22000
0#
0)
#23000
1#
1)
#24000
0#
0)
#25000
1#
1)
#26000
0#
0)
#27000
1#
1)
#28000
0#
0)
#29000
1#
1)
#30000
0#
0)
#31000
1#
1)
#32000
0#
0)
#33000
1#
1)
#34000
0#
0)
#35000
1#
1)
#36000
0#
0)
#37000
1#
1)
#38000
0#
0)
#39000
1#
1)
#40000
#40001
0#
0$
b0000000000 %
b0000000000 &
0)
0*
b0000000000 +
b0000000000 ,
#41001
1#
1)
#42001
0#
0)
#43001
1#
1)
#44001
0#
b0000000101 %
b0000000111 &
b0000001001 '
0)
b0000000101 +
b0000000111 ,
b0000001001 -
#45001
1#
1)
#46001
0#
b1111111111 %
b1111111111 &
b1111111111 '
0)
b1111111111 +
b1111111111 ,
b1111111111 -
#47001
1#
1)
#48001
0#
1$
b0000000000 %
b0000000000 &
b0000000000 '
0)
1*
b0000000000 +
b0000000000 ,
b0000000000 -
#49001
1#
b0000000000000000000000 (
1)
b0000000000000000000000 .
b0000000000000000000000 /
#50001
0#
b1111111111 &
0)
b1111111111 ,
#51001
1#
1)
#52001
0#
b1111111111 %
b0000000000 &
b1111111111 '
0)
b1111111111 +
b0000000000 ,
b1111111111 -
#53001
1#
b0000000000001111111111 (
1)
b0000000000001111111111 .
b0000000000001111111111 /
#54001
0#
b0000000001 %
b0000000001 &
b0000000001 '
0)
b0000000001 +
b0000000001 ,
b0000000001 -
#55001
1#
b0000000000000000000010 (
1)
b0000000000000000000010 .
b0000000000000000000010 /
#56001
0#
b1111111111 %
b0000000000 '
0)
b1111111111 +
b0000000000 -
#57001
1#
b0000000000001111111111 (
1)
b0000000000001111111111 .
b0000000000001111111111 /
#58001
0#
b0000000001 %
b1111111111 &
0)
b0000000001 +
b1111111111 ,
#59001
1#
1)
#60001
0#
b1111111111 %
0)
b1111111111 +
#61001
1#
b0011111111100000000001 (
1)
b0011111111100000000001 .
b0011111111100000000001 /
#62001
0#
b0000000001 '
0)
b0000000001 -
#63001
1#
b0011111111100000000010 (
1)
b0011111111100000000010 .
b0011111111100000000010 /
#64001
0#
b1111111111 '
0)
b1111111111 -
#65001
1#
b0011111111110000000000 (
1)
b0011111111110000000000 .
b0011111111110000000000 /
#66001
0#
0)
#67001
1#
1)
#68001
0#
b1111111110 &
0)
b1111111110 ,
#69001
1#
b0011111111100000000001 (
1)
b0011111111100000000001 .
b0011111111100000000001 /
#70001
0#
b0000000001 &
0)
b0000000001 ,
#71001
1#
b0000000000011111111110 (
1)
b0000000000011111111110 .
b0000000000011111111110 /
#72001
0#
b1111111110 %
b0110101001 &
b0101100110 '
0)
b1111111110 +
b0110101001 ,
b0101100110 -
#73001
1#
b0001101010001000010100 (
1)
b0001101010001000010100 .
b0001101010001000010100 /
#74001
0#
b1111111110 &
b0000000000 '
0)
b1111111110 ,
b0000000000 -
#75001
1#
b0011111111000000000100 (
1)
b0011111111000000000100 .
b0011111111000000000100 /
#76001
0#
b0000000001 %
b0000000001 &
b0000100100 '
0)
b0000000001 +
b0000000001 ,
b0000100100 -
#77001
1#
b0000000000000000100101 (
1)
b0000000000000000100101 .
b0000000000000000100101 /
#78001
0#
b0000011111 %
b1111111101 &
b1111111111 '
0)
b0000011111 +
b1111111101 ,
b1111111111 -
#79001
1#
b0000000111111110100010 (
1)
b0000000111111110100010 .
b0000000111111110100010 /
#80001
0#
b1111011111 %
b1111111110 &
0)
b1111011111 +
b1111111110 ,
#81001
1#
b0011110111100001000001 (
1)
b0011110111100001000001 .
b0011110111100001000001 /
#82001
0#
b0000000001 %
b0000000001 &
0)
b0000000001 +
b0000000001 ,
#83001
1#
b0000000000010000000000 (
1)
b0000000000010000000000 .
b0000000000010000000000 /
#84001
0#
b0000000000 %
b0000010100 &
b0000000000 '
0)
b0000000000 +
b0000010100 ,
b0000000000 -
#85001
1#
b0000000000000000000000 (
1)
b0000000000000000000000 .
b0000000000000000000000 /
#86001
0#
b1100101111 %
b1110110000 &
b0101111111 '
0)
b1100101111 +
b1110110000 ,
b0101111111 -
#87001
1#
b0010111011111011001111 (
1)
b0010111011111011001111 .
b0010111011111011001111 /
#88001
0#
b1101000010 %
b0010001001 &
b1111111111 '
0)
b1101000010 +
b0010001001 ,
b1111111111 -
#89001
1#
b0000011100001001010001 (
1)
b0000011100001001010001 .
b0000011100001001010001 /
#90001
0#
b1111111110 %
b1111111111 &
0)
b1111111110 +
b1111111111 ,
#91001
1#
b0011111111100000000001 (
1)
b0011111111100000000001 .
b0011111111100000000001 /
#92001
0#
b1001101101 %
b1010110101 &
0)
b1001101101 +
b1010110101 ,
#93001
1#
b0001101001010100010000 (
1)
b0001101001010100010000 .
b0001101001010100010000 /
#94001
0#
b1111100100 %
b1010110111 &
0)
b1111100100 +
b1010110111 ,
#95001
1#
b0010101001001111111011 (
1)
b0010101001001111111011 .
b0010101001001111111011 /
#96001
0#
b1101100111 %
b0000000001 &
b1111001011 '
0)
b1101100111 +
b0000000001 ,
b1111001011 -
#97001
1#
b0000000000011100110010 (
1)
b0000000000011100110010 .
b0000000000011100110010 /
#98001
0#
b1111111111 %
b1001101010 &
b0000000001 '
0)
b1111111111 +
b1001101010 ,
b0000000001 -
#99001
1#
b0010011010010110010111 (
1)
b0010011010010110010111 .
b0010011010010110010111 /
#100001
0#
b0000000000 %
b0000000000 &
b0000000000 '
0)
b0000000000 +
b0000000000 ,
b0000000000 -
#101001
1#
b0000000000000000000000 (
1)
b0000000000000000000000 .
b0000000000000000000000 /
#102001
0#
b1110110100 '
0)
b1110110100 -
#103001
1#
b0000000000001110110100 (
1)
b0000000000001110110100 .
b0000000000001110110100 /
#104001
0#
b0111001101 &
b0011101100 '
0)
b0111001101 ,
b0011101100 -
#105001
1#
b0000000000000011101100 (
1)
b0000000000000011101100 .
b0000000000000011101100 /
#106001
0#
b1010000010 %
b1111111111 &
b1111111111 '
0)
b1010000010 +
b1111111111 ,
b1111111111 -
#107001
1#
b0010100000100101111101 (
1)
b0010100000100101111101 .
b0010100000100101111101 /
#108001
0#
b1000000110 %
b0000000000 &
b0000000001 '
0)
b1000000110 +
b0000000000 ,
b0000000001 -
#109001
1#
b0000000000000000000001 (
1)
b0000000000000000000001 .
b0000000000000000000001 /
#110001
0#
b0000000001 %
b0010000011 &
0)
b0000000001 +
b0010000011 ,
#111001
1#
b0000000000000010000100 (
1)
b0000000000000010000100 .
b0000000000000010000100 /
#112001
0#
b0000000000 %
b1011001111 &
b1111111111 '
0)
b0000000000 +
b1011001111 ,
b1111111111 -
#113001
1#
b0000000000001111111111 (
1)
b0000000000001111111111 .
b0000000000001111111111 /
#114001
0#
b0011101011 &
b0000000000 '
0)
b0011101011 ,
b0000000000 -
#115001
1#
b0000000000000000000000 (
1)
b0000000000000000000000 .
b0000000000000000000000 /
#116001
0#
b1111111110 %
b0000000000 &
0)
b1111111110 +
b0000000000 ,
#117001
1#
1)
#118001
0#
b0000000001 %
b1111111111 &
b1100110001 '
0)
b0000000001 +
b1111111111 ,
b1100110001 -
#119001
1#
b0000000000011100110000 (
1)
b0000000000011100110000 .
b0000000000011100110000 /
#120001
0#
b0111000101 %
b0000000001 '
0)
b0111000101 +
b0000000001 -
#121001
1#
b0001110001001000111100 (
1)
b0001110001001000111100 .
b0001110001001000111100 /
#122001
0#
b1111111111 %
b0000000000 &
b0000000000 '
0)
b1111111111 +
b0000000000 ,
b0000000000 -
#123001
1#
b0000000000000000000000 (
1)
b0000000000000000000000 .
b0000000000000000000000 /
#124001
0#
b1111111111 &
b0000000010 '
0)
b1111111111 ,
b0000000010 -
#125001
1#
b0011111111100000000011 (
1)
b0011111111100000000011 .
b0011111111100000000011 /
#126001
0#
b1000111101 %
b0000000000 &
b1111110101 '
0)
b1000111101 +
b0000000000 ,
b1111110101 -
#127001
1#
b0000000000001111110101 (
1)
b0000000000001111110101 .
b0000000000001111110101 /
#128001
0#
b0000000001 %
b1111111111 &
b1101001000 '
0)
b0000000001 +
b1111111111 ,
b1101001000 -
#129001
1#
b0000000000011101000111 (
1)
b0000000000011101000111 .
b0000000000011101000111 /
#130001
0#
b0000000000 %
b1111111110 &
b1100110010 '
0)
b0000000000 +
b1111111110 ,
b1100110010 -
#131001
1#
b0000000000001100110010 (
1)
b0000000000001100110010 .
b0000000000001100110010 /
#132001
0#
b1111111111 %
b0000000000 &
b0000000000 '
0)
b1111111111 +
b0000000000 ,
b0000000000 -
#133001
1#
b0000000000000000000000 (
1)
b0000000000000000000000 .
b0000000000000000000000 /
#134001
0#
b1111011111 %
b1111111111 &
b1111111111 '
0)
b1111011111 +
b1111111111 ,
b1111111111 -
#135001
1#
b0011110111110000100000 (
1)
b0011110111110000100000 .
b0011110111110000100000 /
#136001
0#
b0011101101 %
b0000000001 &
b1111111110 '
0)
b0011101101 +
b0000000001 ,
b1111111110 -
#137001
1#
b0000000000010011101011 (
1)
b0000000000010011101011 .
b0000000000010011101011 /
#138001
0#
b0000000000 %
b0010110100 '
0)
b0000000000 +
b0010110100 -
#139001
1#
b0000000000000010110100 (
1)
b0000000000000010110100 .
b0000000000000010110100 /
#140001
0#
b1111111111 %
b1111111110 '
0)
b1111111111 +
b1111111110 -
#141001
1#
b0000000000011111111101 (
1)
b0000000000011111111101 .
b0000000000011111111101 /
#142001
0#
b0101111000 %
b0100101001 &
0)
b0101111000 +
b0100101001 ,
#143001
1#
b0000011011100000110110 (
1)
b0000011011100000110110 .
b0000011011100000110110 /
#144001
0#
b0000000001 %
b0011110111 &
0)
b0000000001 +
b0011110111 ,
#145001
1#
b0000000000010011110101 (
1)
b0000000000010011110101 .
b0000000000010011110101 /
#146001
0#
b1111111111 %
b0000000001 &
b1110110001 '
0)
b1111111111 +
b0000000001 ,
b1110110001 -
#147001
1#
b0000000000011110110000 (
1)
b0000000000011110110000 .
b0000000000011110110000 /
#148001
0#
b0000000000 %
b1011101010 &
b0000000000 '
0)
b0000000000 +
b1011101010 ,
b0000000000 -
#149001
1#
b0000000000000000000000 (
1)
b0000000000000000000000 .
b0000000000000000000000 /
#150001
0#
b0000000001 %
b0000000001 &
b1101010111 '
0)
b0000000001 +
b0000000001 ,
b1101010111 -
#151001
1#
b0000000000001101011000 (
1)
b0000000000001101011000 .
b0000000000001101011000 /
#152001
0#
b0000000000 %
b0000000000 &
b0000000001 '
0)
b0000000000 +
b0000000000 ,
b0000000001 -
#153001
1#
b0000000000000000000001 (
1)
b0000000000000000000001 .
b0000000000000000000001 /
#154001
0#
b0000000001 %
b0111011001 &
b1111111111 '
0)
b0000000001 +
b0111011001 ,
b1111111111 -
#155001
1#
b0000000000010111011000 (
1)
b0000000000010111011000 .
b0000000000010111011000 /
#156001
0#
b0000000000 %
b1111111111 &
b0000000001 '
0)
b0000000000 +
b1111111111 ,
b0000000001 -
#157001
1#
b0000000000000000000001 (
1)
b0000000000000000000001 .
b0000000000000000000001 /
#158001
0#
b1111111111 %
b0000000001 &
b1111111111 '
0)
b1111111111 +
b0000000001 ,
b1111111111 -
#159001
1#
b0000000000011111111110 (
1)
b0000000000011111111110 .
b0000000000011111111110 /
#160001
0#
b0011000101 %
b0000000000 &
b0000000001 '
0)
b0011000101 +
b0000000000 ,
b0000000001 -
#161001
1#
b0000000000000000000001 (
1)
b0000000000000000000001 .
b0000000000000000000001 /
#162001
0#
b1001101010 %
b0000000001 &
b1110110001 '
0)
b1001101010 +
b0000000001 ,
b1110110001 -
#163001
1#
b0000000000011000011011 (
1)
b0000000000011000011011 .
b0000000000011000011011 /
#164001
0#
b0000000001 %
b0000000000 '
0)
b0000000001 +
b0000000000 -
#165001
1#
b0000000000000000000001 (
1)
b0000000000000000000001 .
b0000000000000000000001 /
#166001
0#
b1101010110 %
b0010001100 &
b0000000001 '
0)
b1101010110 +
b0010001100 ,
b0000000001 -
#167001
1#
b0000011101001100001001 (
1)
b0000011101001100001001 .
b0000011101001100001001 /
#168001
0#
b0000111000 %
b1111111111 &
b0000000100 '
0)
b0000111000 +
b1111111111 ,
b0000000100 -
#169001
1#
b0000001101111111001100 (
1)
b0000001101111111001100 .
b0000001101111111001100 /
#170001
0#
b0000000001 %
b0000000000 &
b1111111111 '
0)
b0000000001 +
b0000000000 ,
b1111111111 -
#171001
1#
b0000000000001111111111 (
1)
b0000000000001111111111 .
b0000000000001111111111 /
#172001
0#
b1111111111 %
b1101111000 &
b1110100000 '
0)
b1111111111 +
b1101111000 ,
b1110100000 -
#173001
1#
b0011011110000000101000 (
1)
b0011011110000000101000 .
b0011011110000000101000 /
#174001
0#
b1000011100 %
b1111111111 &
b1111111111 '
0)
b1000011100 +
b1111111111 ,
b1111111111 -
#175001
1#
b0010000111000111100011 (
1)
b0010000111000111100011 .
b0010000111000111100011 /
#176001
0#
b0011010110 %
b0000000001 &
b0000000001 '
0)
b0011010110 +
b0000000001 ,
b0000000001 -
#177001
1#
b0000000000000011010111 (
1)
b0000000000000011010111 .
b0000000000000011010111 /
#178001
0#
b1101110010 %
b1110101100 &
b1101000101 '
0)
b1101110010 +
b1110101100 ,
b1101000101 -
#179001
1#
b0011001010100111011101 (
1)
b0011001010100111011101 .
b0011001010100111011101 /
#180001
0#
b1000100010 %
b0000000001 &
b0011001001 '
0)
b1000100010 +
b0000000001 ,
b0011001001 -
#181001
1#
b0000000000001011101011 (
1)
b0000000000001011101011 .
b0000000000001011101011 /
#182001
0#
b1111111111 %
b0000000001 '
0)
b1111111111 +
b0000000001 -
#183001
1#
b0000000000010000000000 (
1)
b0000000000010000000000 .
b0000000000010000000000 /
#184001
0#
b0101111001 %
b1111111111 '
0)
b0101111001 +
b1111111111 -
#185001
1#
b0000000000010101111000 (
1)
b0000000000010101111000 .
b0000000000010101111000 /
#186001
0#
b1111111111 %
b1111111110 &
b0110101100 '
0)
b1111111111 +
b1111111110 ,
b0110101100 -
#187001
1#
b0011111111010110101110 (
1)
b0011111111010110101110 .
b0011111111010110101110 /
#188001
0#
b0000000000 %
b0000000000 &
b1111110100 '
0)
b0000000000 +
b0000000000 ,
b1111110100 -
#189001
1#
b0000000000001111110100 (
1)
b0000000000001111110100 .
b0000000000001111110100 /
#190001
0#
b1111111111 %
b1111111110 &
b1100111101 '
0)
b1111111111 +
b1111111110 ,
b1100111101 -
#191001
1#
b0011111111011100111111 (
1)
b0011111111011100111111 .
b0011111111011100111111 /
#192001
0#
b0010011011 %
b0010101011 &
b0000000001 '
0)
b0010011011 +
b0010101011 ,
b0000000001 -
#193001
1#
b0000000110011110001010 (
1)
b0000000110011110001010 .
b0000000110011110001010 /
#194001
0#
b0000000001 %
b1111111111 &
b1110010101 '
0)
b0000000001 +
b1111111111 ,
b1110010101 -
#195001
1#
b0000000000011110010100 (
1)
b0000000000011110010100 .
b0000000000011110010100 /
#196001
0#
b0000000001 '
0)
b0000000001 -
#197001
1#
b0000000000010000000000 (
1)
b0000000000010000000000 .
b0000000000010000000000 /
#198001
0#
b1111111110 %
b0000000001 &
b1111111111 '
0)
b1111111110 +
b0000000001 ,
b1111111111 -
#199001
1#
b0000000000011111111101 (
1)
b0000000000011111111101 .
b0000000000011111111101 /
#200001
0#
b0000000000 &
b1111111110 '
0)
b0000000000 ,
b1111111110 -
#201001
1#
b0000000000001111111110 (
1)
b0000000000001111111110 .
b0000000000001111111110 /
#202001
0#
b1110000110 %
b0011101111 &
b0011100000 '
0)
b1110000110 +
b0011101111 ,
b0011100000 -
#203001
1#
b0000110100101011111010 (
1)
b0000110100101011111010 .
b0000110100101011111010 /
#204001
0#
b0001010101 %
b1111111111 &
b0000000001 '
0)
b0001010101 +
b1111111111 ,
b0000000001 -
#205001
1#
b0000010101001110101100 (
1)
b0000010101001110101100 .
b0000010101001110101100 /
#206001
0#
b0001011001 %
b1111000001 &
b1111111111 '
0)
b0001011001 +
b1111000001 ,
b1111111111 -
#207001
1#
b0000010101001000011000 (
1)
b0000010101001000011000 .
b0000010101001000011000 /
#208001
0#
b0010011011 %
b1101010100 &
0)
b0010011011 +
b1101010100 ,
#209001
1#
b0000100000011111011011 (
1)
b0000100000011111011011 .
b0000100000011111011011 /
#210001
0#
b0000000001 %
b0001011011 &
b1111111110 '
0)
b0000000001 +
b0001011011 ,
b1111111110 -
#211001
1#
b0000000000010001011001 (
1)
b0000000000010001011001 .
b0000000000010001011001 /
#212001
0#
b0011011011 %
b1111111111 &
b1111111111 '
0)
b0011011011 +
b1111111111 ,
b1111111111 -
#213001
1#
b0000110110111100100100 (
1)
b0000110110111100100100 .
b0000110110111100100100 /
#214001
0#
b0000000001 %
b0000000000 &
b0110011110 '
0)
b0000000001 +
b0000000000 ,
b0110011110 -
#215001
1#
b0000000000000110011110 (
1)
b0000000000000110011110 .
b0000000000000110011110 /
#216001
0#
b1011011101 %
b1111111110 '
0)
b1011011101 +
b1111111110 -
#217001
1#
b0000000000001111111110 (
1)
b0000000000001111111110 .
b0000000000001111111110 /
#218001
0#
b0000000000 %
b0110000100 '
0)
b0000000000 +
b0110000100 -
#219001
1#
b0000000000000110000100 (
1)
b0000000000000110000100 .
b0000000000000110000100 /
#220001
0#
b1011110100 %
b0000000001 &
b1111111111 '
0)
b1011110100 +
b0000000001 ,
b1111111111 -
#221001
1#
b0000000000011011110011 (
1)
b0000000000011011110011 .
b0000000000011011110011 /
#222001
0#
b1111111110 %
b0000000000 &
b0000000001 '
0)
b1111111110 +
b0000000000 ,
b0000000001 -
#223001
1#
b0000000000000000000001 (
1)
b0000000000000000000001 .
b0000000000000000000001 /
#224001
0#
b0000110001 %
b0110000100 &
b1111111111 '
0)
b0000110001 +
b0110000100 ,
b1111111111 -
#225001
1#
b0000000100111001000011 (
1)
b0000000100111001000011 .
b0000000100111001000011 /
#226001
0#
b1111111110 %
b0000000000 &
b0011011000 '
0)
b1111111110 +
b0000000000 ,
b0011011000 -
#227001
1#
b0000000000000011011000 (
1)
b0000000000000011011000 .
b0000000000000011011000 /
#228001
0#
b0000000000 %
b1001101010 &
b1111111110 '
0)
b0000000000 +
b1001101010 ,
b1111111110 -
#229001
1#
b0000000000001111111110 (
1)
b0000000000001111111110 .
b0000000000001111111110 /
#230001
0#
b0111011101 %
b0000000001 &
b0000000001 '
0)
b0111011101 +
b0000000001 ,
b0000000001 -
#231001
1#
b0000000000000111011110 (
1)
b0000000000000111011110 .
b0000000000000111011110 /
#232001
0#
b0011101110 %
b1001001100 &
b0110100100 '
0)
b0011101110 +
b1001001100 ,
b0110100100 -
#233001
1#
b0000100010010001001100 (
1)
b0000100010010001001100 .
b0000100010010001001100 /
#234001
0#
b0001010000 %
b1111111111 &
b1010010100 '
0)
b0001010000 +
b1111111111 ,
b1010010100 -
#235001
1#
b0000010100001001000100 (
1)
b0000010100001001000100 .
b0000010100001001000100 /
#236001
0#
b0000000000 %
b0000000001 '
0)
b0000000000 +
b0000000001 -
#237001
1#
b0000000000000000000001 (
1)
b0000000000000000000001 .
b0000000000000000000001 /
#238001
0#
b1111111110 %
b0000000001 &
b1111111111 '
0)
b1111111110 +
b0000000001 ,
b1111111111 -
#239001
1#
b0000000000011111111101 (
1)
b0000000000011111111101 .
b0000000000011111111101 /
#240001
0#
b0000000001 %
b1111111111 &
b0000000000 '
0)
b0000000001 +
b1111111111 ,
b0000000000 -
#241001
1#
b0000000000001111111111 (
1)
b0000000000001111111111 .
b0000000000001111111111 /
#242001
0#
b1111111110 %
b0000000001 &
b1111111110 '
0)
b1111111110 +
b0000000001 ,
b1111111110 -
#243001
1#
b0000000000011111111100 (
1)
b0000000000011111111100 .
b0000000000011111111100 /
#244001
0#
b0010110101 %
b0000000000 '
0)
b0010110101 +
b0000000000 -
#245001
1#
b0000000000000010110101 (
1)
b0000000000000010110101 .
b0000000000000010110101 /
#246001
0#
b0000000000 %
b1111111111 &
b1000001101 '
0)
b0000000000 +
b1111111111 ,
b1000001101 -
#247001
1#
b0000000000001000001101 (
1)
b0000000000001000001101 .
b0000000000001000001101 /
#248001
0#
b0111100101 %
b1101100111 &
b1110010011 '
0)
b0111100101 +
b1101100111 ,
b1110010011 -
#249001
1#
b0001100111010110110110 (
1)
b0001100111010110110110 .
b0001100111010110110110 /
#250001
0#
b0000000001 %
b1111111110 &
b1111001011 '
0)
b0000000001 +
b1111111110 ,
b1111001011 -
#251001
1#
b0000000000011111001001 (
1)
b0000000000011111001001 .
b0000000000011111001001 /
#252001
0#
b1111111111 &
b1000111110 '
0)
b1111111111 ,
b1000111110 -
#253001
1#
b0000000000011000111101 (
1)
b0000000000011000111101 .
b0000000000011000111101 /
#254001
0#
b1111111111 %
b1100011001 &
b0101011100 '
0)
b1111111111 +
b1100011001 ,
b0101011100 -
#255001
1#
b0011000110001001000011 (
1)
b0011000110001001000011 .
b0011000110001001000011 /
#256001
0#
b1010101111 %
b0000000000 &
b0000000001 '
0)
b1010101111 +
b0000000000 ,
b0000000001 -
#257001
1#
b0000000000000000000001 (
1)
b0000000000000000000001 .
b0000000000000000000001 /
#258001
0#
b0000000000 %
b1001000000 &
b0000000000 '
0)
b0000000000 +
b1001000000 ,
b0000000000 -
#259001
1#
b0000000000000000000000 (
1)
b0000000000000000000000 .
b0000000000000000000000 /
#260001
0#
b1111111110 %
b0000000000 &
b1111111111 '
0)
b1111111110 +
b0000000000 ,
b1111111111 -
#261001
1#
b0000000000001111111111 (
1)
b0000000000001111111111 .
b0000000000001111111111 /
#262001
0#
b0000000000 %
b0000000001 &
b0000000001 '
0)
b0000000000 +
b0000000001 ,
b0000000001 -
#263001
1#
b0000000000000000000001 (
1)
b0000000000000000000001 .
b0000000000000000000001 /
#264001
0#
b1111111111 %
b0111111000 &
b0101100110 '
0)
b1111111111 +
b0111111000 ,
b0101100110 -
#265001
1#
b0001111101111101101110 (
1)
b0001111101111101101110 .
b0001111101111101101110 /
#266001
0#
b0000000000 %
b1000010000 &
b1111001110 '
0)
b0000000000 +
b1000010000 ,
b1111001110 -
#267001
1#
b0000000000001111001110 (
1)
b0000000000001111001110 .
b0000000000001111001110 /
#268001
0#
b1111111110 %
b0000000000 &
b1111111111 '
0)
b1111111110 +
b0000000000 ,
b1111111111 -
#269001
1#
b0000000000001111111111 (
1)
b0000000000001111111111 .
b0000000000001111111111 /
#270001
0#
b0000000000 %
b1111111111 &
b0001110110 '
0)
b0000000000 +
b1111111111 ,
b0001110110 -
#271001
1#
b0000000000000001110110 (
1)
b0000000000000001110110 .
b0000000000000001110110 /
#272001
0#
b1110100111 %
b0000010001 &
b0001111110 '
0)
b1110100111 +
b0000010001 ,
b0001111110 -
#273001
1#
b0000000011111010010101 (
1)
b0000000011111010010101 .
b0000000011111010010101 /
#274001
0#
b1111111111 %
b0011010111 &
b0000000000 '
0)
b1111111111 +
b0011010111 ,
b0000000000 -
#275001
1#
b0000110101101100101001 (
1)
b0000110101101100101001 .
b0000110101101100101001 /
#276001
0#
b0000000000 %
b0000000000 &
b0010110110 '
0)
b0000000000 +
b0000000000 ,
b0010110110 -
#277001
1#
b0000000000000010110110 (
1)
b0000000000000010110110 .
b0000000000000010110110 /
#278001
0#
b1111111111 %
b0101100100 &
b1111111111 '
0)
b1111111111 +
b0101100100 ,
b1111111111 -
#279001
1#
b0001011001001010011011 (
1)
b0001011001001010011011 .
b0001011001001010011011 /
#280001
0#
b0000000001 %
b0110111110 &
b0100001111 '
0)
b0000000001 +
b0110111110 ,
b0100001111 -
#281001
1#
b0000000000001011001101 (
1)
b0000000000001011001101 .
b0000000000001011001101 /
#282001
0#
b0000000001 &
b0000000001 '
0)
b0000000001 ,
b0000000001 -
#283001
1#
b0000000000000000000010 (
1)
b0000000000000000000010 .
b0000000000000000000010 /
#284001
0#
b1111111111 %
b0000000000 '
0)
b1111111111 +
b0000000000 -
#285001
1#
b0000000000001111111111 (
1)
b0000000000001111111111 .
b0000000000001111111111 /
#286001
0#
b0000000001 %
b0000000000 &
b1111111110 '
0)
b0000000001 +
b0000000000 ,
b1111111110 -
#287001
1#
b0000000000001111111110 (
1)
b0000000000001111111110 .
b0000000000001111111110 /
#288001
0#
b0000000000 %
b0100001001 &
b1111111111 '
0)
b0000000000 +
b0100001001 ,
b1111111111 -
#289001
1#
b0000000000001111111111 (
1)
b0000000000001111111111 .
b0000000000001111111111 /
#290001
0#
b0000000001 %
b0000000001 &
b0000000000 '
0)
b0000000001 +
b0000000001 ,
b0000000000 -
#291001
1#
b0000000000000000000001 (
1)
b0000000000000000000001 .
b0000000000000000000001 /
#292001
0#
b0000000001 '
0)
b0000000001 -
#293001
1#
b0000000000000000000010 (
1)
b0000000000000000000010 .
b0000000000000000000010 /
#294001
0#
b0011100010 %
b1111111111 &
b0101000010 '
0)
b0011100010 +
b1111111111 ,
b0101000010 -
#295001
1#
b0000111000100001100000 (
1)
b0000111000100001100000 .
b0000111000100001100000 /
#296001
0#
b0101010011 %
b0000000001 &
b1111111110 '
0)
b0101010011 +
b0000000001 ,
b1111111110 -
#297001
1#
b0000000000010101010001 (
1)
b0000000000010101010001 .
b0000000000010101010001 /
#298001
0#
b0111010010 %
b1100110100 &
b0000000001 '
0)
b0111010010 +
b1100110100 ,
b0000000001 -
#299001
1#
b0001011101010010101001 (
1)
b0001011101010010101001 .
b0001011101010010101001 /
#300001
0#
b1101000001 %
b0000000001 &
b1111111110 '
0)
b1101000001 +
b0000000001 ,
b1111111110 -
#301001
1#
b0000000000011100111111 (
1)
b0000000000011100111111 .
b0000000000011100111111 /
#302001
0#
b1111111111 %
b1111111111 &
b0000000000 '
0)
b1111111111 +
b1111111111 ,
b0000000000 -
#303001
1#
b0011111111100000000001 (
1)
b0011111111100000000001 .
b0011111111100000000001 /
#304001
0#
b0000000001 %
b0100001011 '
0)
b0000000001 +
b0100001011 -
#305001
1#
b0000000000010100001010 (
1)
b0000000000010100001010 .
b0000000000010100001010 /
#306001
0#
b0000000001 '
0)
b0000000001 -
#307001
1#
b0000000000010000000000 (
1)
b0000000000010000000000 .
b0000000000010000000000 /
#308001
0#
b1111111110 %
b0000000001 &
b1111111111 '
0)
b1111111110 +
b0000000001 ,
b1111111111 -
#309001
1#
b0000000000011111111101 (
1)
b0000000000011111111101 .
b0000000000011111111101 /
#310001
0#
b1010100000 %
b0000000000 '
0)
b1010100000 +
b0000000000 -
#311001
1#
b0000000000001010100000 (
1)
b0000000000001010100000 .
b0000000000001010100000 /
#312001
0#
b0000000001 %
b1111111111 &
b1011001000 '
0)
b0000000001 +
b1111111111 ,
b1011001000 -
#313001
1#
b0000000000011011000111 (
1)
b0000000000011011000111 .
b0000000000011011000111 /
#314001
0#
b1111111110 &
b0000000001 '
0)
b1111111110 ,
b0000000001 -
#315001
1#
b0000000000001111111111 (
1)
b0000000000001111111111 .
b0000000000001111111111 /
#316001
0#
b0010000010 %
b1111111111 &
0)
b0010000010 +
b1111111111 ,
#317001
1#
b0000100000011101111111 (
1)
b0000100000011101111111 .
b0000100000011101111111 /
#318001
0#
b1111111111 %
b0000000000 &
b0000000000 '
0)
b1111111111 +
b0000000000 ,
b0000000000 -
#319001
1#
b0000000000000000000000 (
1)
b0000000000000000000000 .
b0000000000000000000000 /
#320001
0#
b1111111111 &
b1111111110 '
0)
b1111111111 ,
b1111111110 -
#321001
1#
b0011111111101111111111 (
1)
b0011111111101111111111 .
b0011111111101111111111 /
#322001
0#
b0000000000 %
b1111111111 '
0)
b0000000000 +
b1111111111 -
#323001
1#
b0000000000001111111111 (
1)
b0000000000001111111111 .
b0000000000001111111111 /
#324001
0#
b1000100010 %
b0000000001 &
b0000000001 '
0)
b1000100010 +
b0000000001 ,
b0000000001 -
#325001
1#
b0000000000001000100011 (
1)
b0000000000001000100011 .
b0000000000001000100011 /
#326001
0#
b0000000001 %
b1111111110 &
b1111111110 '
0)
b0000000001 +
b1111111110 ,
b1111111110 -
#327001
1#
b0000000000011111111100 (
1)
b0000000000011111111100 .
b0000000000011111111100 /
