mySA/2D_array/pe.v
module pe #(
  parameter integer DATA_WIDTH = 10
) (
    input clk,
    input compute,
    input  logic unsigned [DATA_WIDTH-1:0] north,
    input  logic unsigned [DATA_WIDTH-1:0] west,
    output logic unsigned [DATA_WIDTH-1:0] east,
    output  logic unsigned [DATA_WIDTH-1:0] south,
    input init
);
    reg [(2*DATA_WIDTH)+1:0] state;

    always @ (posedge clk) 
        if (init)
            state <= 0;
        else
        if (compute)
            // MAC: state = state + north * west;
            state <= state + (north*west);

    assign east = state[DATA_WIDTH-1:0];
    assign south = north;

endmodule

mySA/2D_array/dump.vcd
$version Generated by VerilatedVcd $end
$timescale 1ps $end
 $scope module  $end
  $var wire 1 # clk $end
  $var wire 1 $ compute $end
  $var wire 10 % north [9:0] $end
  $var wire 10 & west [9:0] $end
  $var wire 10 ' east [9:0] $end
  $var wire 10 ( south [9:0] $end
  $var wire 1 ) init $end
  $scope module pe $end
   $var wire 32 2 DATA_WIDTH [31:0] $end
   $var wire 1 * clk $end
   $var wire 1 + compute $end
   $var wire 10 , north [9:0] $end
   $var wire 10 - west [9:0] $end
   $var wire 10 . east [9:0] $end
   $var wire 10 / south [9:0] $end
   $var wire 1 0 init $end
   $var wire 22 1 state [21:0] $end
  $upscope $end
 $upscope $end
$enddefinitions $end


#0
0#
0$
b0000000000 %
b0000000000 &
b0000000000 '
b0000000000 (
1)
0*
0+
b0000000000 ,
b0000000000 -
b0000000000 .
b0000000000 /
10
b0000000000000000000000 1
b00000000000000000000000000001010 2
#1000
1#
1*
#2000
0#
0)
0*
00
#3000
1#
1*
#4000
0#
1$
b1111111111 %
b1111111111 &
b1111111111 (
0*
1+
b1111111111 ,
b1111111111 -
b1111111111 /
#5000
1#
b0000000001 '
1*
b0000000001 .
b0011111111100000000001 1
#6000
#6001
#7001
0#
0$
b0000000000 %
b0000000000 &
b0000000000 (
1)
0*
0+
b0000000000 ,
b0000000000 -
b0000000000 /
10
#8001
1#
b0000000000 '
1*
b0000000000 .
b0000000000000000000000 1
#9001
0#
b0000000011 %
b0000000100 &
b0000000011 (
0)
0*
b0000000011 ,
b0000000100 -
b0000000011 /
00
#10001
1#
1*
#11001
0#
1$
0*
1+
#12001
1#
b0000001100 '
1*
b0000001100 .
b0000000000000000001100 1
#13001
0#
b0000000101 %
b0000000110 &
b0000000101 (
0*
b0000000101 ,
b0000000110 -
b0000000101 /
#14001
1#
b0000101010 '
1*
b0000101010 .
b0000000000000000101010 1
#15001
0#
0$
b0000000111 %
b0000000111 &
b0000000111 (
0*
0+
b0000000111 ,
b0000000111 -
b0000000111 /
#16001
1#
1*
#17001
0#
1$
b1111111111 %
b1111111111 &
b1111111111 (
0*
1+
b1111111111 ,
b1111111111 -
b1111111111 /
#18001
1#
b0000101011 '
1*
b0000101011 .
b0011111111100000101011 1
#19001
0#
0$
b0000000000 %
b0000000000 &
b0000000000 (
1)
0*
0+
b0000000000 ,
b0000000000 -
b0000000000 /
10
#20001
1#
b0000000000 '
1*
b0000000000 .
b0000000000000000000000 1
#21001
0#
1$
b0000000010 %
b0000000010 &
b0000000010 (
0)
0*
1+
b0000000010 ,
b0000000010 -
b0000000010 /
00
#22001
1#
b0000000100 '
1*
b0000000100 .
b0000000000000000000100 1
